pytanis/__init__.py
pytanis/config.py
pytanis/factory.py
pytanis/google.py
pytanis/highs.py
pytanis/py.typed
pytanis/review.py
pytanis/utils.py
pytanis/communication/__init__.py
pytanis/communication/base.py
pytanis/communication/helpdesk_adapter.py
pytanis/communication/mailgun_adapter.py
pytanis/helpdesk/__init__.py
pytanis/helpdesk/client.py
pytanis/helpdesk/mail.py
pytanis/helpdesk/models.py
pytanis/mailgun/__init__.py
pytanis/mailgun/mail.py
pytanis/pretalx/__init__.py
pytanis/pretalx/client.py
pytanis/pretalx/models.py
pytanis/pretalx/schema.yml
pytanis/pretalx/utils.py
pytanis-0.9.6.dist-info/METADATA
pytanis-0.9.6.dist-info/WHEEL
pytanis-0.9.6.dist-info/licenses/AUTHORS.md
pytanis-0.9.6.dist-info/licenses/LICENSE.txt
pytanis-0.9.6.dist-info/RECORD
