Metadata-Version: 2.4
Name: Pytanis
Version: 0.9.6
Summary: Utilities for the program organization of conferences using Pretalx
Project-URL: Documentation, https://pioneershub.github.io/pytanis/
Project-URL: Sponsor, https://github.com/sponsors/PioneersHub
Project-URL: Tracker, https://github.com/PioneersHub/pytanis/issues
Project-URL: Source, https://github.com/PioneersHub/pytanis
Author-email: Florian Wilhelm <Florian.Wilhelm@gmail.com>
License-Expression: MIT
License-File: AUTHORS.md
License-File: LICENSE.txt
Keywords: cfp,conference,google sheet,gsheet,helpdesk,pretalx
Classifier: Development Status :: 4 - Beta
Classifier: Operating System :: OS Independent
Classifier: Programming Language :: Python
Classifier: Programming Language :: Python :: 3.12
Classifier: Programming Language :: Python :: 3.13
Classifier: Programming Language :: Python :: Implementation :: CPython
Classifier: Topic :: Communications :: Email
Classifier: Topic :: Software Development :: Libraries
Classifier: Topic :: Utilities
Requires-Python: >=3.12
Requires-Dist: httpx
Requires-Dist: httpx-auth
Requires-Dist: openpyxl>=3.1.5
Requires-Dist: pandas-stubs<3,>=2
Requires-Dist: pandas<3,>=2
Requires-Dist: pydantic>=2.5
Requires-Dist: structlog
Requires-Dist: tomli
Requires-Dist: tqdm
Provides-Extra: all
Requires-Dist: gspread-dataframe; extra == 'all'
Requires-Dist: gspread-formatting; extra == 'all'
Requires-Dist: gspread<6.0; extra == 'all'
Requires-Dist: highspy; extra == 'all'
Requires-Dist: ipywidgets; extra == 'all'
Requires-Dist: jupyter>=1.1.1; extra == 'all'
Requires-Dist: pillow; extra == 'all'
Requires-Dist: pyomo>=6.9.1; extra == 'all'
Requires-Dist: seaborn>=0.13.2; extra == 'all'
Requires-Dist: webcolors; extra == 'all'
Provides-Extra: google
Requires-Dist: gspread-dataframe; extra == 'google'
Requires-Dist: gspread-formatting; extra == 'google'
Requires-Dist: gspread<6.0; extra == 'google'
Requires-Dist: webcolors; extra == 'google'
Provides-Extra: jupyter
Requires-Dist: ipywidgets; extra == 'jupyter'
Requires-Dist: jupyter>=1.1.1; extra == 'jupyter'
Requires-Dist: seaborn>=0.13.2; extra == 'jupyter'
Provides-Extra: optimization
Requires-Dist: highspy; extra == 'optimization'
Requires-Dist: pyomo>=6.9.1; extra == 'optimization'
